picoca/__init__.py
picoca/ca.py
picoca/crypto.py
picoca/main.py
picoca-1.0.0.dist-info/LICENSE.md
picoca-1.0.0.dist-info/METADATA
picoca-1.0.0.dist-info/WHEEL
picoca-1.0.0.dist-info/entry_points.txt
picoca-1.0.0.dist-info/top_level.txt
picoca-1.0.0.dist-info/RECORD
